wdsf_api/__init__.py
wdsf_api/client.py
wdsf_api/deprecated_parser.py
wdsf_api/deprecated_session.py
wdsf_api/schema.py
wdsf_api-0.1.2.dist-info/METADATA
wdsf_api-0.1.2.dist-info/WHEEL
wdsf_api-0.1.2.dist-info/licenses/LICENSE
wdsf_api-0.1.2.dist-info/RECORD
