Metadata-Version: 2.3
Name: wdsf-api
Version: 0.1.2
Summary: WDSF API Python Client (unofficial)
Project-URL: Homepage, https://github.com/dancesport-live/wdsf-api-python-client
Project-URL: Issues, https://github.com/dancesport-live/wdsf-api-python-client/issues
License-File: LICENSE
Keywords: API,DanceSport,WDSF,World DanceSport Federation
Classifier: Development Status :: 3 - Alpha
Classifier: Intended Audience :: Developers
Classifier: License :: OSI Approved :: Apache Software License
Classifier: Natural Language :: English
Classifier: Operating System :: OS Independent
Classifier: Programming Language :: Python :: 3
Requires-Dist: pydantic
Requires-Dist: uplink
